{
	"stable-version": "19.1",
	"stable-date": "2017-07-08",
	"stable-date-text": "8 July 2017",
	"stable-release-notes": "http://nzbget.net/history-latest",
	"stable-update-rate": "0,1,2,5,10,20,40,70,100",
	"testing-version": "20.0",
	"testing-revision": "r2147",
	"testing-date": "2017-10-29",
	"testing-date-text": "29 October 2017",
	"testing-release-notes": "http://nzbget.net/history-latest-testing",
	"testing-update-rate": "0,5,20,50,100",
	"android-version": "1.1",
	"android-revision": "r13"
}
